zyt_fileio_utils/__init__.py
zyt_fileio_utils/configio.py
zyt_fileio_utils/jsonio.py
zyt_fileio_utils/textio.py
zyt_fileio_utils/tomlio.py
zyt_fileio_utils/utils.py
zyt_fileio_utils/yamlio.py
zyt_fileio_utils-0.2.0.dist-info/LICENSE
zyt_fileio_utils-0.2.0.dist-info/METADATA
zyt_fileio_utils-0.2.0.dist-info/WHEEL
zyt_fileio_utils-0.2.0.dist-info/top_level.txt
zyt_fileio_utils-0.2.0.dist-info/RECORD
