Metadata-Version: 2.1
Name: zyt-fileio-utils
Version: 0.2.0
Summary: A utility package of file io for Python projects
Home-page: https://github.com/VerySeriousMan/zyt_fileio_utils
Author: ZhangYuetao
Author-email: zhang894171707@gmail.com
License: UNKNOWN
Platform: UNKNOWN
Classifier: Programming Language :: Python :: 3
Classifier: License :: OSI Approved :: MIT License
Classifier: Operating System :: OS Independent
Requires-Python: >=3.6
License-File: LICENSE
